{
    "metadata": {
        "provider": "ED3",
        "scraped_at": "2026-07-17 11:14:08 MST",
        "source": "ED3 OMS Mobile Outage Service",
        "scraper_version": "1.0.0"
    },
    "summary": {
        "outage_count": 1,
        "customers_affected": 1,
        "total_customers": 36390
    },
    "outages": [
        {
            "latitude": 32.922998646510116,
            "longitude": -111.96577827672925,
            "boundary": "T-101743",
            "customers": 1,
            "cause": "110 - Maintenance",
            "comments": "CauseFound",
            "start_time": "2026-07-17 10:30:59 MST",
            "etr": null,
            "pole_number": "101743"
        }
    ]
}